LICENSE
README.rst
setup.py
Flask_SQL_Pro.egg-info/PKG-INFO
Flask_SQL_Pro.egg-info/SOURCES.txt
Flask_SQL_Pro.egg-info/dependency_links.txt
Flask_SQL_Pro.egg-info/requires.txt
Flask_SQL_Pro.egg-info/top_level.txt
flask_sql_pro/__init__.py
flask_sql_pro/db.py
flask_sql_pro/sql_loader.py