Metadata-Version: 2.1
Name: Flask-SQL-Pro
Version: 4.6
Summary: Based on Flask-SQLAlchemy, extract SQL statements, use Jinja2 syntax to achieve dynamic SQL, support contextual transactions, support paging
Author: miaokela
Author-email: 2972799448@qq.com
Maintainer: miaokela
Maintainer-email: 2972799448@qq.com
Classifier: Programming Language :: Python
Classifier: Programming Language :: Python :: 3.7
Classifier: Programming Language :: Python :: Implementation :: CPython
Classifier: Programming Language :: Python :: Implementation :: PyPy
License-File: LICENSE
